wincertstore.py
wincertstore-0.2.1.dist-info/LICENSE
wincertstore-0.2.1.dist-info/METADATA
wincertstore-0.2.1.dist-info/WHEEL
wincertstore-0.2.1.dist-info/top_level.txt
wincertstore-0.2.1.dist-info/RECORD
