Metadata-Version: 1.2
Name: wincertstore
Version: 0.2.1
Summary: Python module to extract CA and CRL certs from Windows' cert store (ctypes based).
Home-page: https://github.com/tiran/wincertstore
Author: Christian Heimes
Author-email: christian@python.org
Maintainer: Christian Heimes
Maintainer-email: christian@python.org
License: PSFL
Download-URL: http://pypi.python.org/pypi/wincertstore
Keywords: windows cert ssl ca crl
Platform: Windows
Classifier: Development Status :: 4 - Beta
Classifier: Intended Audience :: Developers
Classifier: License :: OSI Approved :: Python Software Foundation License
Classifier: Natural Language :: English
Classifier: Operating System :: Microsoft :: Windows
Classifier: Programming Language :: Python
Classifier: Programming Language :: Python :: 2
Classifier: Programming Language :: Python :: 2.7
Classifier: Programming Language :: Python :: 3
Requires-Python: >=2.7,!=3.0.*,!=3.1.*,<3.4.*
